{"startTime":1660852556262,"endTime":1660853241364,"playlistCode":"CTF-Standard-6","region":"eu","server":"gs-eu-4","gameMode":"CaptureTheFlag","size":6,"teams":["Blue","Red"],"players":[{"displayName":"Drinky McDumbass","playfabId":"84C09631ABBCDA0E","team":"Blue","kills":21,"deaths":29,"kd":0.7241379310344828,"oldRating":{"numGamesPlayedInPlaylist":44,"mu":37.06375031027938,"sigma":6.046052127178433,"lowerSkillEstimate":18.925593928744085,"tier":"SILVER_II","formattedTier":"Silver II","tierNumber":5,"tierImageUrl":"http://placeholder"},"newRating":{"numGamesPlayedInPlaylist":45,"mu":38.54544634952879,"sigma":6.12013981115509,"lowerSkillEstimate":20.18502691606352,"tier":"SILVER_II","formattedTier":"Silver II","tierNumber":5,"tierImageUrl":"http://placeholder"}},{"displayName":"Psycho","playfabId":"C42975C9A8E4E66B","team":"Blue","kills":49,"deaths":35,"kd":1.4,"oldRating":{"numGamesPlayedInPlaylist":62,"mu":66.74258707122155,"sigma":6.2456152438192625,"lowerSkillEstimate":48.00574133976376,"tier":"PLATINUM_II","formattedTier":"Platinum II","tierNumber":11,"tierImageUrl":"http://placeholder"},"newRating":{"numGamesPlayedInPlaylist":63,"mu":68.31668872923441,"sigma":6.298232501011027,"lowerSkillEstimate":49.421991226201335,"tier":"PLATINUM_III","formattedTier":"Platinum III","tierNumber":12,"tierImageUrl":"http://placeholder"}},{"displayName":"challz","playfabId":"47167D5CB3751A2C","team":"Blue","kills":45,"deaths":31,"kd":1.4516129032258065,"oldRating":{"numGamesPlayedInPlaylist":4,"mu":34.0395729335632,"sigma":10.497237055701891,"lowerSkillEstimate":2.547861766457526,"tier":"UNRANKED","formattedTier":"Unranked","tierNumber":0,"tierImageUrl":"http://placeholder"},"newRating":{"numGamesPlayedInPlaylist":5,"mu":38.29525840185297,"sigma":9.87372976082142,"lowerSkillEstimate":8.674069119388712,"tier":"UNRANKED","formattedTier":"Unranked","tierNumber":0,"tierImageUrl":"http://placeholder"}},{"displayName":"Mouren","playfabId":"1A2F81E7C5DFF825","team":"Red","kills":17,"deaths":43,"kd":0.3953488372093023,"oldRating":{"numGamesPlayedInPlaylist":2,"mu":34.533330992148784,"sigma":12.894684423178646,"lowerSkillEstimate":-4.150722277387153,"tier":"UNRANKED","formattedTier":"Unranked","tierNumber":0,"tierImageUrl":"http://placeholder"},"newRating":{"numGamesPlayedInPlaylist":3,"mu":28.165021171667387,"sigma":11.592595630156778,"lowerSkillEstimate":-6.612765718802944,"tier":"UNRANKED","formattedTier":"Unranked","tierNumber":0,"tierImageUrl":"http://placeholder"}},{"displayName":"Haste","playfabId":"C19637F2290726EB","team":"Red","kills":42,"deaths":37,"kd":1.135135135135135,"oldRating":{"numGamesPlayedInPlaylist":371,"mu":61.86411499833441,"sigma":6.171076663073517,"lowerSkillEstimate":43.35088500911385,"tier":"PLATINUM_I","formattedTier":"Platinum I","tierNumber":10,"tierImageUrl":"http://placeholder"},"newRating":{"numGamesPlayedInPlaylist":372,"mu":60.32487871422112,"sigma":6.231772219538093,"lowerSkillEstimate":41.62956205560684,"tier":"PLATINUM_I","formattedTier":"Platinum I","tierNumber":10,"tierImageUrl":"http://placeholder"}},{"displayName":"Leon","playfabId":"5F4BAE52BEDDF22","team":"Red","kills":36,"deaths":35,"kd":1.0285714285714285,"oldRating":{"numGamesPlayedInPlaylist":336,"mu":43.16075905948228,"sigma":6.014147894839819,"lowerSkillEstimate":25.118315374962826,"tier":"SILVER_III","formattedTier":"Silver III","tierNumber":6,"tierImageUrl":"http://placeholder"},"newRating":{"numGamesPlayedInPlaylist":337,"mu":41.69355774965352,"sigma":6.091623135774085,"lowerSkillEstimate":23.41868834233127,"tier":"SILVER_III","formattedTier":"Silver III","tierNumber":6,"tierImageUrl":"http://placeholder"}}],"result":{"isTie":false,"winner":"Blue"},"matchQuality":0.44191982446007044,"teamWinProbabilities":{"Blue":0.470367481657254,"Red":0.5296325183427459},"teamRoundWins":{"Blue":2,"Red":0},"totalRounds":2,"rounds":[{"startTime":1660852590516,"endTime":1660852905863,"mapName":"ctf_dopamine","events":[{"type":"PLAYER_KILL","timestamp":1660852608590,"killerPlayfabId":"C42975C9A8E4E66B","killerTeam":"Blue","victimPlayfabId":"1A2F81E7C5DFF825","victimTeam":"Red","weaponName":"SteyrAUG"},{"type":"PLAYER_KILL","timestamp":1660852609240,"killerPlayfabId":"5F4BAE52BEDDF22","killerTeam":"Red","victimPlayfabId":"84C09631ABBCDA0E","victimTeam":"Blue","weaponName":"Rheinmetall"},{"type":"PLAYER_KILL","timestamp":1660852613096,"killerPlayfabId":"C42975C9A8E4E66B","killerTeam":"Blue","victimPlayfabId":"5F4BAE52BEDDF22","victimTeam":"Red","weaponName":"SteyrAUG"},{"type":"PLAYER_KILL","timestamp":1660852614801,"killerPlayfabId":"C19637F2290726EB","killerTeam":"Red","victimPlayfabId":"C42975C9A8E4E66B","victimTeam":"Blue","weaponName":"SteyrAUG"},{"type":"PLAYER_KILL","timestamp":1660852617919,"killerPlayfabId":"1A2F81E7C5DFF825","killerTeam":"Red","victimPlayfabId":"47167D5CB3751A2C","victimTeam":"Blue","weaponName":"SteyrAUG"},{"type":"PLAYER_KILL","timestamp":1660852620153,"killerPlayfabId":"84C09631ABBCDA0E","killerTeam":"Blue","victimPlayfabId":"1A2F81E7C5DFF825","victimTeam":"Red","weaponName":"Kalashnikov"},{"type":"PLAYER_KILL","timestamp":1660852622970,"killerPlayfabId":"84C09631ABBCDA0E","killerTeam":"Blue","victimPlayfabId":"C19637F2290726EB","victimTeam":"Red","weaponName":"Kalashnikov"},{"type":"PLAYER_KILL","timestamp":1660852625994,"killerPlayfabId":"C42975C9A8E4E66B","killerTeam":"Blue","victimPlayfabId":"1A2F81E7C5DFF825","victimTeam":"Red","weaponName":"Knife"},{"type":"PLAYER_KILL","timestamp":1660852628445,"killerPlayfabId":"C19637F2290726EB","killerTeam":"Red","victimPlayfabId":"C42975C9A8E4E66B","victimTeam":"Blue","weaponName":"RGD5"},{"type":"PLAYER_KILL","timestamp":1660852630846,"killerPlayfabId":"5F4BAE52BEDDF22","killerTeam":"Red","victimPlayfabId":"84C09631ABBCDA0E","victimTeam":"Blue","weaponName":"Rheinmetall"},{"type":"PLAYER_KILL","timestamp":1660852634897,"killerPlayfabId":"47167D5CB3751A2C","killerTeam":"Blue","victimPlayfabId":"5F4BAE52BEDDF22","victimTeam":"Red","weaponName":"Kalashnikov"},{"type":"PLAYER_KILL","timestamp":1660852636755,"killerPlayfabId":"C19637F2290726EB","killerTeam":"Red","victimPlayfabId":"47167D5CB3751A2C","victimTeam":"Blue","weaponName":"SteyrAUG"},{"type":"PLAYER_KILL","timestamp":1660852637839,"killerPlayfabId":"C42975C9A8E4E66B","killerTeam":"Blue","victimPlayfabId":"1A2F81E7C5DFF825","victimTeam":"Red","weaponName":"SteyrAUG"},{"type":"PLAYER_KILL","timestamp":1660852643390,"killerPlayfabId":"C42975C9A8E4E66B","killerTeam":"Blue","victimPlayfabId":"5F4BAE52BEDDF22","victimTeam":"Red","weaponName":"SteyrAUG"},{"type":"PLAYER_KILL","timestamp":1660852643791,"killerPlayfabId":"84C09631ABBCDA0E","killerTeam":"Blue","victimPlayfabId":"C19637F2290726EB","victimTeam":"Red","weaponName":"Kalashnikov"},{"type":"PLAYER_KILL","timestamp":1660852644774,"killerPlayfabId":"1A2F81E7C5DFF825","killerTeam":"Red","victimPlayfabId":"84C09631ABBCDA0E","victimTeam":"Blue","weaponName":"Knife"},{"type":"PLAYER_KILL","timestamp":1660852651261,"killerPlayfabId":"C19637F2290726EB","killerTeam":"Red","victimPlayfabId":"C42975C9A8E4E66B","victimTeam":"Blue","weaponName":"SteyrAUG"},{"type":"PLAYER_KILL","timestamp":1660852658030,"killerPlayfabId":"C42975C9A8E4E66B","killerTeam":"Blue","victimPlayfabId":"5F4BAE52BEDDF22","victimTeam":"Red","weaponName":"SteyrAUG"},{"type":"PLAYER_KILL","timestamp":1660852660331,"killerPlayfabId":"47167D5CB3751A2C","killerTeam":"Blue","victimPlayfabId":"1A2F81E7C5DFF825","victimTeam":"Red","weaponName":"Kalashnikov"},{"type":"PLAYER_KILL","timestamp":1660852661332,"killerPlayfabId":"C19637F2290726EB","killerTeam":"Red","victimPlayfabId":"C42975C9A8E4E66B","victimTeam":"Blue","weaponName":"SteyrAUG"},{"type":"FLAG_CAP","timestamp":1660852666161,"cappingTeam":"Red","playfabId":"C19637F2290726EB"},{"type":"PLAYER_KILL","timestamp":1660852666812,"killerPlayfabId":"47167D5CB3751A2C","killerTeam":"Blue","victimPlayfabId":"5F4BAE52BEDDF22","victimTeam":"Red","weaponName":"Kalashnikov"},{"type":"PLAYER_KILL","timestamp":1660852666960,"killerPlayfabId":"5F4BAE52BEDDF22","killerTeam":"Red","victimPlayfabId":"84C09631ABBCDA0E","victimTeam":"Blue","weaponName":"Rheinmetall"},{"type":"PLAYER_KILL","timestamp":1660852670136,"killerPlayfabId":"C42975C9A8E4E66B","killerTeam":"Blue","victimPlayfabId":"1A2F81E7C5DFF825","victimTeam":"Red","weaponName":"SteyrAUG"},{"type":"PLAYER_KILL","timestamp":1660852671840,"killerPlayfabId":"C19637F2290726EB","killerTeam":"Red","victimPlayfabId":"47167D5CB3751A2C","victimTeam":"Blue","weaponName":"SteyrAUG"},{"type":"PLAYER_KILL","timestamp":1660852672272,"killerPlayfabId":"5F4BAE52BEDDF22","killerTeam":"Red","victimPlayfabId":"C42975C9A8E4E66B","victimTeam":"Blue","weaponName":"Kalashnikov"},{"type":"PLAYER_KILL","timestamp":1660852679604,"killerPlayfabId":"84C09631ABBCDA0E","killerTeam":"Blue","victimPlayfabId":"1A2F81E7C5DFF825","victimTeam":"Red","weaponName":"Kalashnikov"},{"type":"PLAYER_KILL","timestamp":1660852679671,"killerPlayfabId":"1A2F81E7C5DFF825","killerTeam":"Red","victimPlayfabId":"84C09631ABBCDA0E","victimTeam":"Blue","weaponName":"Knife"},{"type":"PLAYER_KILL","timestamp":1660852679905,"killerPlayfabId":"C42975C9A8E4E66B","killerTeam":"Blue","victimPlayfabId":"5F4BAE52BEDDF22","victimTeam":"Red","weaponName":"RGD5"},{"type":"PLAYER_KILL","timestamp":1660852682379,"killerPlayfabId":"C42975C9A8E4E66B","killerTeam":"Blue","victimPlayfabId":"C19637F2290726EB","victimTeam":"Red","weaponName":"Knife"},{"type":"PLAYER_KILL","timestamp":1660852682946,"killerPlayfabId":"1A2F81E7C5DFF825","killerTeam":"Red","victimPlayfabId":"C42975C9A8E4E66B","victimTeam":"Blue","weaponName":"Knife"},{"type":"PLAYER_KILL","timestamp":1660852684063,"killerPlayfabId":"47167D5CB3751A2C","killerTeam":"Blue","victimPlayfabId":"1A2F81E7C5DFF825","victimTeam":"Red","weaponName":"Knife"},{"type":"PLAYER_KILL","timestamp":1660852688748,"killerPlayfabId":"5F4BAE52BEDDF22","killerTeam":"Red","victimPlayfabId":"47167D5CB3751A2C","victimTeam":"Blue","weaponName":"Kalashnikov"},{"type":"PLAYER_KILL","timestamp":1660852690699,"killerPlayfabId":"84C09631ABBCDA0E","killerTeam":"Blue","victimPlayfabId":"C19637F2290726EB","victimTeam":"Red","weaponName":"Kalashnikov"},{"type":"PLAYER_KILL","timestamp":1660852692167,"killerPlayfabId":"C42975C9A8E4E66B","killerTeam":"Blue","victimPlayfabId":"5F4BAE52BEDDF22","victimTeam":"Red","weaponName":"SteyrAUG"},{"type":"PLAYER_KILL","timestamp":1660852692751,"killerPlayfabId":"84C09631ABBCDA0E","killerTeam":"Blue","victimPlayfabId":"1A2F81E7C5DFF825","victimTeam":"Red","weaponName":"Knife"},{"type":"PLAYER_KILL","timestamp":1660852695443,"killerPlayfabId":"C19637F2290726EB","killerTeam":"Red","victimPlayfabId":"84C09631ABBCDA0E","victimTeam":"Blue","weaponName":"SteyrAUG"},{"type":"PLAYER_KILL","timestamp":1660852697577,"killerPlayfabId":"C19637F2290726EB","killerTeam":"Red","victimPlayfabId":"C42975C9A8E4E66B","victimTeam":"Blue","weaponName":"SteyrAUG"},{"type":"PLAYER_KILL","timestamp":1660852704663,"killerPlayfabId":"1A2F81E7C5DFF825","killerTeam":"Red","victimPlayfabId":"47167D5CB3751A2C","victimTeam":"Blue","weaponName":"SteyrAUG"},{"type":"PLAYER_KILL","timestamp":1660852704830,"killerPlayfabId":"C42975C9A8E4E66B","killerTeam":"Blue","victimPlayfabId":"1A2F81E7C5DFF825","victimTeam":"Red","weaponName":"RGD5"},{"type":"PLAYER_KILL","timestamp":1660852705363,"killerPlayfabId":"C42975C9A8E4E66B","killerTeam":"Blue","victimPlayfabId":"C19637F2290726EB","victimTeam":"Red","weaponName":"Kalashnikov"},{"type":"PLAYER_KILL","timestamp":1660852707815,"killerPlayfabId":"C42975C9A8E4E66B","killerTeam":"Blue","victimPlayfabId":"5F4BAE52BEDDF22","victimTeam":"Red","weaponName":"Kalashnikov"},{"type":"PLAYER_KILL","timestamp":1660852710323,"killerPlayfabId":"84C09631ABBCDA0E","killerTeam":"Blue","victimPlayfabId":"C19637F2290726EB","victimTeam":"Red","weaponName":"Knife"},{"type":"PLAYER_KILL","timestamp":1660852712207,"killerPlayfabId":"5F4BAE52BEDDF22","killerTeam":"Red","victimPlayfabId":"84C09631ABBCDA0E","victimTeam":"Blue","weaponName":"RGD5"},{"type":"PLAYER_KILL","timestamp":1660852712440,"killerPlayfabId":"1A2F81E7C5DFF825","killerTeam":"Red","victimPlayfabId":"C42975C9A8E4E66B","victimTeam":"Blue","weaponName":"Knife"},{"type":"PLAYER_KILL","timestamp":1660852713191,"killerPlayfabId":"47167D5CB3751A2C","killerTeam":"Blue","victimPlayfabId":"5F4BAE52BEDDF22","victimTeam":"Red","weaponName":"Kalashnikov"},{"type":"PLAYER_KILL","timestamp":1660852716109,"killerPlayfabId":"1A2F81E7C5DFF825","killerTeam":"Red","victimPlayfabId":"47167D5CB3751A2C","victimTeam":"Blue","weaponName":"Knife"},{"type":"PLAYER_KILL","timestamp":1660852717693,"killerPlayfabId":"84C09631ABBCDA0E","killerTeam":"Blue","victimPlayfabId":"1A2F81E7C5DFF825","victimTeam":"Red","weaponName":"SteyrAUG"},{"type":"PLAYER_KILL","timestamp":1660852720711,"killerPlayfabId":"84C09631ABBCDA0E","killerTeam":"Blue","victimPlayfabId":"C19637F2290726EB","victimTeam":"Red","weaponName":"SteyrAUG"},{"type":"PLAYER_KILL","timestamp":1660852720714,"killerPlayfabId":"C19637F2290726EB","killerTeam":"Red","victimPlayfabId":"84C09631ABBCDA0E","victimTeam":"Blue","weaponName":"SteyrAUG"},{"type":"PLAYER_KILL","timestamp":1660852721911,"killerPlayfabId":"C42975C9A8E4E66B","killerTeam":"Blue","victimPlayfabId":"5F4BAE52BEDDF22","victimTeam":"Red","weaponName":"Kalashnikov"},{"type":"PLAYER_KILL","timestamp":1660852726948,"killerPlayfabId":"5F4BAE52BEDDF22","killerTeam":"Red","victimPlayfabId":"C42975C9A8E4E66B","victimTeam":"Blue","weaponName":"Kalashnikov"},{"type":"PLAYER_KILL","timestamp":1660852729714,"killerPlayfabId":"84C09631ABBCDA0E","killerTeam":"Blue","victimPlayfabId":"1A2F81E7C5DFF825","victimTeam":"Red","weaponName":"SteyrAUG"},{"type":"PLAYER_KILL","timestamp":1660852730555,"killerPlayfabId":"C19637F2290726EB","killerTeam":"Red","victimPlayfabId":"47167D5CB3751A2C","victimTeam":"Blue","weaponName":"SteyrAUG"},{"type":"PLAYER_KILL","timestamp":1660852733682,"killerPlayfabId":"C19637F2290726EB","killerTeam":"Red","victimPlayfabId":"84C09631ABBCDA0E","victimTeam":"Blue","weaponName":"SteyrAUG"},{"type":"PLAYER_KILL","timestamp":1660852741460,"killerPlayfabId":"47167D5CB3751A2C","killerTeam":"Blue","victimPlayfabId":"5F4BAE52BEDDF22","victimTeam":"Red","weaponName":"Kalashnikov"},{"type":"PLAYER_KILL","timestamp":1660852742343,"killerPlayfabId":"84C09631ABBCDA0E","killerTeam":"Blue","victimPlayfabId":"C19637F2290726EB","victimTeam":"Red","weaponName":"RGD5"},{"type":"PLAYER_KILL","timestamp":1660852742810,"killerPlayfabId":"C42975C9A8E4E66B","killerTeam":"Blue","victimPlayfabId":"1A2F81E7C5DFF825","victimTeam":"Red","weaponName":"Kalashnikov"},{"type":"PLAYER_KILL","timestamp":1660852747436,"killerPlayfabId":"47167D5CB3751A2C","killerTeam":"Blue","victimPlayfabId":"1A2F81E7C5DFF825","victimTeam":"Red","weaponName":"Knife"},{"type":"PLAYER_KILL","timestamp":1660852751005,"killerPlayfabId":"5F4BAE52BEDDF22","killerTeam":"Red","victimPlayfabId":"84C09631ABBCDA0E","victimTeam":"Blue","weaponName":"Kalashnikov"},{"type":"PLAYER_KILL","timestamp":1660852751022,"killerPlayfabId":"C42975C9A8E4E66B","killerTeam":"Blue","victimPlayfabId":"C19637F2290726EB","victimTeam":"Red","weaponName":"Kalashnikov"},{"type":"PLAYER_KILL","timestamp":1660852751772,"killerPlayfabId":"47167D5CB3751A2C","killerTeam":"Blue","victimPlayfabId":"5F4BAE52BEDDF22","victimTeam":"Red","weaponName":"Kalashnikov"},{"type":"FLAG_CAP","timestamp":1660852756059,"cappingTeam":"Blue","playfabId":"47167D5CB3751A2C"},{"type":"PLAYER_KILL","timestamp":1660852757974,"killerPlayfabId":"1A2F81E7C5DFF825","killerTeam":"Red","victimPlayfabId":"C42975C9A8E4E66B","victimTeam":"Blue","weaponName":"Knife"},{"type":"PLAYER_KILL","timestamp":1660852760099,"killerPlayfabId":"84C09631ABBCDA0E","killerTeam":"Blue","victimPlayfabId":"C19637F2290726EB","victimTeam":"Red","weaponName":"RGD5"},{"type":"PLAYER_KILL","timestamp":1660852762816,"killerPlayfabId":"5F4BAE52BEDDF22","killerTeam":"Red","victimPlayfabId":"47167D5CB3751A2C","victimTeam":"Blue","weaponName":"Kalashnikov"},{"type":"PLAYER_KILL","timestamp":1660852765234,"killerPlayfabId":"C42975C9A8E4E66B","killerTeam":"Blue","victimPlayfabId":"1A2F81E7C5DFF825","victimTeam":"Red","weaponName":"Kalashnikov"},{"type":"PLAYER_KILL","timestamp":1660852769317,"killerPlayfabId":"C19637F2290726EB","killerTeam":"Red","victimPlayfabId":"84C09631ABBCDA0E","victimTeam":"Blue","weaponName":"SteyrAUG"},{"type":"PLAYER_KILL","timestamp":1660852770817,"killerPlayfabId":"5F4BAE52BEDDF22","killerTeam":"Red","victimPlayfabId":"5F4BAE52BEDDF22","victimTeam":"Red","weaponName":"RPG"},{"type":"PLAYER_KILL","timestamp":1660852773788,"killerPlayfabId":"47167D5CB3751A2C","killerTeam":"Blue","victimPlayfabId":"C19637F2290726EB","victimTeam":"Red","weaponName":"Kalashnikov"},{"type":"PLAYER_KILL","timestamp":1660852775272,"killerPlayfabId":"1A2F81E7C5DFF825","killerTeam":"Red","victimPlayfabId":"47167D5CB3751A2C","victimTeam":"Blue","weaponName":"Knife"},{"type":"PLAYER_KILL","timestamp":1660852776223,"killerPlayfabId":"5F4BAE52BEDDF22","killerTeam":"Red","victimPlayfabId":"C42975C9A8E4E66B","victimTeam":"Blue","weaponName":"Kalashnikov"},{"type":"PLAYER_KILL","timestamp":1660852782475,"killerPlayfabId":"47167D5CB3751A2C","killerTeam":"Blue","victimPlayfabId":"5F4BAE52BEDDF22","victimTeam":"Red","weaponName":"Kalashnikov"},{"type":"PLAYER_KILL","timestamp":1660852783797,"killerPlayfabId":"C42975C9A8E4E66B","killerTeam":"Blue","victimPlayfabId":"C19637F2290726EB","victimTeam":"Red","weaponName":"Kalashnikov"},{"type":"PLAYER_KILL","timestamp":1660852788386,"killerPlayfabId":"5F4BAE52BEDDF22","killerTeam":"Red","victimPlayfabId":"C42975C9A8E4E66B","victimTeam":"Blue","weaponName":"RGD5"},{"type":"PLAYER_KILL","timestamp":1660852789635,"killerPlayfabId":"47167D5CB3751A2C","killerTeam":"Blue","victimPlayfabId":"1A2F81E7C5DFF825","victimTeam":"Red","weaponName":"Kalashnikov"},{"type":"PLAYER_KILL","timestamp":1660852790211,"killerPlayfabId":"C19637F2290726EB","killerTeam":"Red","victimPlayfabId":"47167D5CB3751A2C","victimTeam":"Blue","weaponName":"SteyrAUG"},{"type":"PLAYER_KILL","timestamp":1660852796483,"killerPlayfabId":"47167D5CB3751A2C","killerTeam":"Blue","victimPlayfabId":"C19637F2290726EB","victimTeam":"Red","weaponName":"Kalashnikov"},{"type":"PLAYER_KILL","timestamp":1660852800523,"killerPlayfabId":"C42975C9A8E4E66B","killerTeam":"Blue","victimPlayfabId":"5F4BAE52BEDDF22","victimTeam":"Red","weaponName":"Kalashnikov"},{"type":"PLAYER_KILL","timestamp":1660852801091,"killerPlayfabId":"C42975C9A8E4E66B","killerTeam":"Blue","victimPlayfabId":"1A2F81E7C5DFF825","victimTeam":"Red","weaponName":"Kalashnikov"},{"type":"FLAG_CAP","timestamp":1660852802777,"cappingTeam":"Blue","playfabId":"84C09631ABBCDA0E"},{"type":"PLAYER_KILL","timestamp":1660852806727,"killerPlayfabId":"47167D5CB3751A2C","killerTeam":"Blue","victimPlayfabId":"47167D5CB3751A2C","victimTeam":"Blue","weaponName":"N/A"},{"type":"PLAYER_KILL","timestamp":1660852810211,"killerPlayfabId":"84C09631ABBCDA0E","killerTeam":"Blue","victimPlayfabId":"5F4BAE52BEDDF22","victimTeam":"Red","weaponName":"RGD5"},{"type":"PLAYER_KILL","timestamp":1660852810512,"killerPlayfabId":"C19637F2290726EB","killerTeam":"Red","victimPlayfabId":"C42975C9A8E4E66B","victimTeam":"Blue","weaponName":"SteyrAUG"},{"type":"PLAYER_KILL","timestamp":1660852818123,"killerPlayfabId":"C42975C9A8E4E66B","killerTeam":"Blue","victimPlayfabId":"1A2F81E7C5DFF825","victimTeam":"Red","weaponName":"RGD5"},{"type":"PLAYER_KILL","timestamp":1660852819174,"killerPlayfabId":"C42975C9A8E4E66B","killerTeam":"Blue","victimPlayfabId":"5F4BAE52BEDDF22","victimTeam":"Red","weaponName":"Kalashnikov"},{"type":"PLAYER_KILL","timestamp":1660852823609,"killerPlayfabId":"C19637F2290726EB","killerTeam":"Red","victimPlayfabId":"47167D5CB3751A2C","victimTeam":"Blue","weaponName":"SteyrAUG"},{"type":"PLAYER_KILL","timestamp":1660852825192,"killerPlayfabId":"5F4BAE52BEDDF22","killerTeam":"Red","victimPlayfabId":"C42975C9A8E4E66B","victimTeam":"Blue","weaponName":"Kalashnikov"},{"type":"PLAYER_KILL","timestamp":1660852829060,"killerPlayfabId":"47167D5CB3751A2C","killerTeam":"Blue","victimPlayfabId":"1A2F81E7C5DFF825","victimTeam":"Red","weaponName":"RGD5"},{"type":"PLAYER_KILL","timestamp":1660852831744,"killerPlayfabId":"C42975C9A8E4E66B","killerTeam":"Blue","victimPlayfabId":"5F4BAE52BEDDF22","victimTeam":"Red","weaponName":"Kalashnikov"},{"type":"PLAYER_KILL","timestamp":1660852831961,"killerPlayfabId":"5F4BAE52BEDDF22","killerTeam":"Red","victimPlayfabId":"C42975C9A8E4E66B","victimTeam":"Blue","weaponName":"Kalashnikov"},{"type":"PLAYER_KILL","timestamp":1660852837183,"killerPlayfabId":"47167D5CB3751A2C","killerTeam":"Blue","victimPlayfabId":"C19637F2290726EB","victimTeam":"Red","weaponName":"Knife"},{"type":"PLAYER_KILL","timestamp":1660852837733,"killerPlayfabId":"5F4BAE52BEDDF22","killerTeam":"Red","victimPlayfabId":"47167D5CB3751A2C","victimTeam":"Blue","weaponName":"Kalashnikov"},{"type":"PLAYER_KILL","timestamp":1660852843688,"killerPlayfabId":"C19637F2290726EB","killerTeam":"Red","victimPlayfabId":"C42975C9A8E4E66B","victimTeam":"Blue","weaponName":"SteyrAUG"},{"type":"PLAYER_KILL","timestamp":1660852844991,"killerPlayfabId":"47167D5CB3751A2C","killerTeam":"Blue","victimPlayfabId":"1A2F81E7C5DFF825","victimTeam":"Red","weaponName":"Kalashnikov"},{"type":"PLAYER_KILL","timestamp":1660852850356,"killerPlayfabId":"C19637F2290726EB","killerTeam":"Red","victimPlayfabId":"C42975C9A8E4E66B","victimTeam":"Blue","weaponName":"RGD5"},{"type":"PLAYER_KILL","timestamp":1660852852170,"killerPlayfabId":"47167D5CB3751A2C","killerTeam":"Blue","victimPlayfabId":"C19637F2290726EB","victimTeam":"Red","weaponName":"Kalashnikov"},{"type":"PLAYER_KILL","timestamp":1660852852256,"killerPlayfabId":"C19637F2290726EB","killerTeam":"Red","victimPlayfabId":"47167D5CB3751A2C","victimTeam":"Blue","weaponName":"SteyrAUG"},{"type":"PLAYER_KILL","timestamp":1660852859640,"killerPlayfabId":"C19637F2290726EB","killerTeam":"Red","victimPlayfabId":"C42975C9A8E4E66B","victimTeam":"Blue","weaponName":"SteyrAUG"},{"type":"PLAYER_KILL","timestamp":1660852862724,"killerPlayfabId":"47167D5CB3751A2C","killerTeam":"Blue","victimPlayfabId":"C19637F2290726EB","victimTeam":"Red","weaponName":"Kalashnikov"},{"type":"PLAYER_KILL","timestamp":1660852862957,"killerPlayfabId":"47167D5CB3751A2C","killerTeam":"Blue","victimPlayfabId":"47167D5CB3751A2C","victimTeam":"Blue","weaponName":"RGD5"},{"type":"PLAYER_KILL","timestamp":1660852869485,"killerPlayfabId":"C42975C9A8E4E66B","killerTeam":"Blue","victimPlayfabId":"C19637F2290726EB","victimTeam":"Red","weaponName":"Kalashnikov"},{"type":"PLAYER_KILL","timestamp":1660852870769,"killerPlayfabId":"47167D5CB3751A2C","killerTeam":"Blue","victimPlayfabId":"1A2F81E7C5DFF825","victimTeam":"Red","weaponName":"RGD5"},{"type":"PLAYER_KILL","timestamp":1660852876954,"killerPlayfabId":"5F4BAE52BEDDF22","killerTeam":"Red","victimPlayfabId":"C42975C9A8E4E66B","victimTeam":"Blue","weaponName":"Kalashnikov"},{"type":"PLAYER_KILL","timestamp":1660852887105,"killerPlayfabId":"C19637F2290726EB","killerTeam":"Red","victimPlayfabId":"47167D5CB3751A2C","victimTeam":"Blue","weaponName":"SteyrAUG"},{"type":"PLAYER_KILL","timestamp":1660852887404,"killerPlayfabId":"84C09631ABBCDA0E","killerTeam":"Blue","victimPlayfabId":"1A2F81E7C5DFF825","victimTeam":"Red","weaponName":"SteyrAUG"},{"type":"PLAYER_KILL","timestamp":1660852893557,"killerPlayfabId":"47167D5CB3751A2C","killerTeam":"Blue","victimPlayfabId":"C19637F2290726EB","victimTeam":"Red","weaponName":"Kalashnikov"},{"type":"PLAYER_KILL","timestamp":1660852900033,"killerPlayfabId":"47167D5CB3751A2C","killerTeam":"Blue","victimPlayfabId":"C19637F2290726EB","victimTeam":"Red","weaponName":"Kalashnikov"},{"type":"PLAYER_KILL","timestamp":1660852903285,"killerPlayfabId":"1A2F81E7C5DFF825","killerTeam":"Red","victimPlayfabId":"47167D5CB3751A2C","victimTeam":"Blue","weaponName":"Dragunov"},{"type":"PLAYER_KILL","timestamp":1660852904642,"killerPlayfabId":"C42975C9A8E4E66B","killerTeam":"Blue","victimPlayfabId":"5F4BAE52BEDDF22","victimTeam":"Red","weaponName":"RGD5"}],"result":{"isTie":false,"winner":"Blue"},"blueCaps":2,"redCaps":1,"playerKillsAndDeaths":{"84C09631ABBCDA0E":{"kills":14,"deaths":11},"C42975C9A8E4E66B":{"kills":25,"deaths":19},"47167D5CB3751A2C":{"kills":20,"deaths":15},"1A2F81E7C5DFF825":{"kills":10,"deaths":22},"C19637F2290726EB":{"kills":20,"deaths":19},"5F4BAE52BEDDF22":{"kills":15,"deaths":18}}},{"startTime":1660852926915,"endTime":1660853241364,"mapName":"ctf_rotten","events":[{"type":"PLAYER_KILL","timestamp":1660852944959,"killerPlayfabId":"47167D5CB3751A2C","killerTeam":"Blue","victimPlayfabId":"C19637F2290726EB","victimTeam":"Red","weaponName":"SteyrAUG"},{"type":"PLAYER_KILL","timestamp":1660852945576,"killerPlayfabId":"84C09631ABBCDA0E","killerTeam":"Blue","victimPlayfabId":"1A2F81E7C5DFF825","victimTeam":"Red","weaponName":"RPG"},{"type":"PLAYER_KILL","timestamp":1660852951336,"killerPlayfabId":"5F4BAE52BEDDF22","killerTeam":"Red","victimPlayfabId":"84C09631ABBCDA0E","victimTeam":"Blue","weaponName":"SteyrAUG"},{"type":"PLAYER_KILL","timestamp":1660852953654,"killerPlayfabId":"C19637F2290726EB","killerTeam":"Red","victimPlayfabId":"47167D5CB3751A2C","victimTeam":"Blue","weaponName":"Knife"},{"type":"PLAYER_KILL","timestamp":1660852957254,"killerPlayfabId":"C19637F2290726EB","killerTeam":"Red","victimPlayfabId":"C42975C9A8E4E66B","victimTeam":"Blue","weaponName":"RGD5"},{"type":"PLAYER_KILL","timestamp":1660852959662,"killerPlayfabId":"47167D5CB3751A2C","killerTeam":"Blue","victimPlayfabId":"1A2F81E7C5DFF825","victimTeam":"Red","weaponName":"RGD5"},{"type":"PLAYER_KILL","timestamp":1660852962393,"killerPlayfabId":"47167D5CB3751A2C","killerTeam":"Blue","victimPlayfabId":"C19637F2290726EB","victimTeam":"Red","weaponName":"SteyrAUG"},{"type":"PLAYER_KILL","timestamp":1660852965013,"killerPlayfabId":"47167D5CB3751A2C","killerTeam":"Blue","victimPlayfabId":"1A2F81E7C5DFF825","victimTeam":"Red","weaponName":"Knife"},{"type":"PLAYER_KILL","timestamp":1660852966871,"killerPlayfabId":"84C09631ABBCDA0E","killerTeam":"Blue","victimPlayfabId":"5F4BAE52BEDDF22","victimTeam":"Red","weaponName":"RocketLauncher"},{"type":"PLAYER_KILL","timestamp":1660852967604,"killerPlayfabId":"C19637F2290726EB","killerTeam":"Red","victimPlayfabId":"84C09631ABBCDA0E","victimTeam":"Blue","weaponName":"RGD5"},{"type":"PLAYER_KILL","timestamp":1660852968166,"killerPlayfabId":"C42975C9A8E4E66B","killerTeam":"Blue","victimPlayfabId":"C19637F2290726EB","victimTeam":"Red","weaponName":"SteyrAUG"},{"type":"PLAYER_KILL","timestamp":1660852968281,"killerPlayfabId":"C19637F2290726EB","killerTeam":"Red","victimPlayfabId":"47167D5CB3751A2C","victimTeam":"Blue","weaponName":"SteyrAUG"},{"type":"PLAYER_KILL","timestamp":1660852973082,"killerPlayfabId":"5F4BAE52BEDDF22","killerTeam":"Red","victimPlayfabId":"C42975C9A8E4E66B","victimTeam":"Blue","weaponName":"Kalashnikov"},{"type":"PLAYER_KILL","timestamp":1660852977260,"killerPlayfabId":"84C09631ABBCDA0E","killerTeam":"Blue","victimPlayfabId":"C19637F2290726EB","victimTeam":"Red","weaponName":"RocketLauncher"},{"type":"PLAYER_KILL","timestamp":1660852978131,"killerPlayfabId":"47167D5CB3751A2C","killerTeam":"Blue","victimPlayfabId":"5F4BAE52BEDDF22","victimTeam":"Red","weaponName":"SteyrAUG"},{"type":"PLAYER_KILL","timestamp":1660852982316,"killerPlayfabId":"C42975C9A8E4E66B","killerTeam":"Blue","victimPlayfabId":"1A2F81E7C5DFF825","victimTeam":"Red","weaponName":"Spas12"},{"type":"PLAYER_KILL","timestamp":1660852987336,"killerPlayfabId":"C19637F2290726EB","killerTeam":"Red","victimPlayfabId":"84C09631ABBCDA0E","victimTeam":"Blue","weaponName":"SteyrAUG"},{"type":"PLAYER_KILL","timestamp":1660852991193,"killerPlayfabId":"5F4BAE52BEDDF22","killerTeam":"Red","victimPlayfabId":"C42975C9A8E4E66B","victimTeam":"Blue","weaponName":"Kalashnikov"},{"type":"PLAYER_KILL","timestamp":1660852991243,"killerPlayfabId":"C42975C9A8E4E66B","killerTeam":"Blue","victimPlayfabId":"5F4BAE52BEDDF22","victimTeam":"Red","weaponName":"Spas12"},{"type":"PLAYER_KILL","timestamp":1660852996680,"killerPlayfabId":"47167D5CB3751A2C","killerTeam":"Blue","victimPlayfabId":"C19637F2290726EB","victimTeam":"Red","weaponName":"SteyrAUG"},{"type":"PLAYER_KILL","timestamp":1660852998130,"killerPlayfabId":"1A2F81E7C5DFF825","killerTeam":"Red","victimPlayfabId":"C42975C9A8E4E66B","victimTeam":"Blue","weaponName":"MP5"},{"type":"PLAYER_KILL","timestamp":1660853001748,"killerPlayfabId":"5F4BAE52BEDDF22","killerTeam":"Red","victimPlayfabId":"84C09631ABBCDA0E","victimTeam":"Blue","weaponName":"Kalashnikov"},{"type":"PLAYER_KILL","timestamp":1660853003065,"killerPlayfabId":"C19637F2290726EB","killerTeam":"Red","victimPlayfabId":"C42975C9A8E4E66B","victimTeam":"Blue","weaponName":"Knife"},{"type":"PLAYER_KILL","timestamp":1660853008351,"killerPlayfabId":"47167D5CB3751A2C","killerTeam":"Blue","victimPlayfabId":"C19637F2290726EB","victimTeam":"Red","weaponName":"SteyrAUG"},{"type":"PLAYER_KILL","timestamp":1660853010869,"killerPlayfabId":"C42975C9A8E4E66B","killerTeam":"Blue","victimPlayfabId":"5F4BAE52BEDDF22","victimTeam":"Red","weaponName":"Kalashnikov"},{"type":"PLAYER_KILL","timestamp":1660853019197,"killerPlayfabId":"47167D5CB3751A2C","killerTeam":"Blue","victimPlayfabId":"C19637F2290726EB","victimTeam":"Red","weaponName":"SteyrAUG"},{"type":"PLAYER_KILL","timestamp":1660853019380,"killerPlayfabId":"5F4BAE52BEDDF22","killerTeam":"Red","victimPlayfabId":"C42975C9A8E4E66B","victimTeam":"Blue","weaponName":"Kalashnikov"},{"type":"PLAYER_KILL","timestamp":1660853023182,"killerPlayfabId":"84C09631ABBCDA0E","killerTeam":"Blue","victimPlayfabId":"1A2F81E7C5DFF825","victimTeam":"Red","weaponName":"RocketLauncher"},{"type":"PLAYER_KILL","timestamp":1660853026853,"killerPlayfabId":"47167D5CB3751A2C","killerTeam":"Blue","victimPlayfabId":"5F4BAE52BEDDF22","victimTeam":"Red","weaponName":"SteyrAUG"},{"type":"PLAYER_KILL","timestamp":1660853026984,"killerPlayfabId":"C19637F2290726EB","killerTeam":"Red","victimPlayfabId":"84C09631ABBCDA0E","victimTeam":"Blue","weaponName":"SteyrAUG"},{"type":"FLAG_CAP","timestamp":1660853028116,"cappingTeam":"Blue","playfabId":"47167D5CB3751A2C"},{"type":"PLAYER_KILL","timestamp":1660853032839,"killerPlayfabId":"C19637F2290726EB","killerTeam":"Red","victimPlayfabId":"84C09631ABBCDA0E","victimTeam":"Blue","weaponName":"RGD5"},{"type":"PLAYER_KILL","timestamp":1660853033592,"killerPlayfabId":"C19637F2290726EB","killerTeam":"Red","victimPlayfabId":"47167D5CB3751A2C","victimTeam":"Blue","weaponName":"SteyrAUG"},{"type":"PLAYER_KILL","timestamp":1660853036884,"killerPlayfabId":"C19637F2290726EB","killerTeam":"Red","victimPlayfabId":"C42975C9A8E4E66B","victimTeam":"Blue","weaponName":"Knife"},{"type":"PLAYER_KILL","timestamp":1660853036917,"killerPlayfabId":"C42975C9A8E4E66B","killerTeam":"Blue","victimPlayfabId":"5F4BAE52BEDDF22","victimTeam":"Red","weaponName":"Kalashnikov"},{"type":"PLAYER_KILL","timestamp":1660853039303,"killerPlayfabId":"C19637F2290726EB","killerTeam":"Red","victimPlayfabId":"84C09631ABBCDA0E","victimTeam":"Blue","weaponName":"SteyrAUG"},{"type":"PLAYER_KILL","timestamp":1660853044538,"killerPlayfabId":"C42975C9A8E4E66B","killerTeam":"Blue","victimPlayfabId":"C19637F2290726EB","victimTeam":"Red","weaponName":"Kalashnikov"},{"type":"PLAYER_KILL","timestamp":1660853044705,"killerPlayfabId":"47167D5CB3751A2C","killerTeam":"Blue","victimPlayfabId":"5F4BAE52BEDDF22","victimTeam":"Red","weaponName":"SteyrAUG"},{"type":"PLAYER_KILL","timestamp":1660853045781,"killerPlayfabId":"C42975C9A8E4E66B","killerTeam":"Blue","victimPlayfabId":"1A2F81E7C5DFF825","victimTeam":"Red","weaponName":"Knife"},{"type":"PLAYER_KILL","timestamp":1660853049873,"killerPlayfabId":"C19637F2290726EB","killerTeam":"Red","victimPlayfabId":"47167D5CB3751A2C","victimTeam":"Blue","weaponName":"SteyrAUG"},{"type":"PLAYER_KILL","timestamp":1660853054342,"killerPlayfabId":"C42975C9A8E4E66B","killerTeam":"Blue","victimPlayfabId":"C19637F2290726EB","victimTeam":"Red","weaponName":"Kalashnikov"},{"type":"PLAYER_KILL","timestamp":1660853056467,"killerPlayfabId":"5F4BAE52BEDDF22","killerTeam":"Red","victimPlayfabId":"C42975C9A8E4E66B","victimTeam":"Blue","weaponName":"Kalashnikov"},{"type":"PLAYER_KILL","timestamp":1660853060043,"killerPlayfabId":"5F4BAE52BEDDF22","killerTeam":"Red","victimPlayfabId":"47167D5CB3751A2C","victimTeam":"Blue","weaponName":"Kalashnikov"},{"type":"PLAYER_KILL","timestamp":1660853061844,"killerPlayfabId":"84C09631ABBCDA0E","killerTeam":"Blue","victimPlayfabId":"1A2F81E7C5DFF825","victimTeam":"Red","weaponName":"RPG"},{"type":"PLAYER_KILL","timestamp":1660853062044,"killerPlayfabId":"1A2F81E7C5DFF825","killerTeam":"Red","victimPlayfabId":"84C09631ABBCDA0E","victimTeam":"Blue","weaponName":"RGD5"},{"type":"PLAYER_KILL","timestamp":1660853069623,"killerPlayfabId":"C19637F2290726EB","killerTeam":"Red","victimPlayfabId":"C42975C9A8E4E66B","victimTeam":"Blue","weaponName":"SteyrAUG"},{"type":"PLAYER_KILL","timestamp":1660853070907,"killerPlayfabId":"47167D5CB3751A2C","killerTeam":"Blue","victimPlayfabId":"C19637F2290726EB","victimTeam":"Red","weaponName":"SteyrAUG"},{"type":"PLAYER_KILL","timestamp":1660853075101,"killerPlayfabId":"C42975C9A8E4E66B","killerTeam":"Blue","victimPlayfabId":"1A2F81E7C5DFF825","victimTeam":"Red","weaponName":"Kalashnikov"},{"type":"PLAYER_KILL","timestamp":1660853076326,"killerPlayfabId":"5F4BAE52BEDDF22","killerTeam":"Red","victimPlayfabId":"47167D5CB3751A2C","victimTeam":"Blue","weaponName":"Kalashnikov"},{"type":"PLAYER_KILL","timestamp":1660853080400,"killerPlayfabId":"C42975C9A8E4E66B","killerTeam":"Blue","victimPlayfabId":"1A2F81E7C5DFF825","victimTeam":"Red","weaponName":"RGD5"},{"type":"PLAYER_KILL","timestamp":1660853085012,"killerPlayfabId":"C42975C9A8E4E66B","killerTeam":"Blue","victimPlayfabId":"C19637F2290726EB","victimTeam":"Red","weaponName":"Kalashnikov"},{"type":"PLAYER_KILL","timestamp":1660853089049,"killerPlayfabId":"C19637F2290726EB","killerTeam":"Red","victimPlayfabId":"84C09631ABBCDA0E","victimTeam":"Blue","weaponName":"RGD5"},{"type":"PLAYER_KILL","timestamp":1660853090731,"killerPlayfabId":"C19637F2290726EB","killerTeam":"Red","victimPlayfabId":"C42975C9A8E4E66B","victimTeam":"Blue","weaponName":"Knife"},{"type":"PLAYER_KILL","timestamp":1660853095415,"killerPlayfabId":"C19637F2290726EB","killerTeam":"Red","victimPlayfabId":"47167D5CB3751A2C","victimTeam":"Blue","weaponName":"Knife"},{"type":"PLAYER_KILL","timestamp":1660853097759,"killerPlayfabId":"84C09631ABBCDA0E","killerTeam":"Blue","victimPlayfabId":"5F4BAE52BEDDF22","victimTeam":"Red","weaponName":"RocketLauncher"},{"type":"PLAYER_KILL","timestamp":1660853101813,"killerPlayfabId":"C42975C9A8E4E66B","killerTeam":"Blue","victimPlayfabId":"1A2F81E7C5DFF825","victimTeam":"Red","weaponName":"Kalashnikov"},{"type":"PLAYER_KILL","timestamp":1660853103280,"killerPlayfabId":"5F4BAE52BEDDF22","killerTeam":"Red","victimPlayfabId":"84C09631ABBCDA0E","victimTeam":"Blue","weaponName":"Kalashnikov"},{"type":"PLAYER_KILL","timestamp":1660853104314,"killerPlayfabId":"C42975C9A8E4E66B","killerTeam":"Blue","victimPlayfabId":"C19637F2290726EB","victimTeam":"Red","weaponName":"Knife"},{"type":"PLAYER_KILL","timestamp":1660853107231,"killerPlayfabId":"5F4BAE52BEDDF22","killerTeam":"Red","victimPlayfabId":"C42975C9A8E4E66B","victimTeam":"Blue","weaponName":"Kalashnikov"},{"type":"PLAYER_KILL","timestamp":1660853108965,"killerPlayfabId":"47167D5CB3751A2C","killerTeam":"Blue","victimPlayfabId":"C19637F2290726EB","victimTeam":"Red","weaponName":"RGD5"},{"type":"PLAYER_KILL","timestamp":1660853111433,"killerPlayfabId":"47167D5CB3751A2C","killerTeam":"Blue","victimPlayfabId":"1A2F81E7C5DFF825","victimTeam":"Red","weaponName":"SteyrAUG"},{"type":"PLAYER_KILL","timestamp":1660853116086,"killerPlayfabId":"C19637F2290726EB","killerTeam":"Red","victimPlayfabId":"84C09631ABBCDA0E","victimTeam":"Blue","weaponName":"SteyrAUG"},{"type":"PLAYER_KILL","timestamp":1660853116236,"killerPlayfabId":"C42975C9A8E4E66B","killerTeam":"Blue","victimPlayfabId":"5F4BAE52BEDDF22","victimTeam":"Red","weaponName":"Kalashnikov"},{"type":"PLAYER_KILL","timestamp":1660853117903,"killerPlayfabId":"47167D5CB3751A2C","killerTeam":"Blue","victimPlayfabId":"1A2F81E7C5DFF825","victimTeam":"Red","weaponName":"SteyrAUG"},{"type":"PLAYER_KILL","timestamp":1660853123121,"killerPlayfabId":"5F4BAE52BEDDF22","killerTeam":"Red","victimPlayfabId":"C42975C9A8E4E66B","victimTeam":"Blue","weaponName":"RGD5"},{"type":"PLAYER_KILL","timestamp":1660853124222,"killerPlayfabId":"1A2F81E7C5DFF825","killerTeam":"Red","victimPlayfabId":"47167D5CB3751A2C","victimTeam":"Blue","weaponName":"Kalashnikov"},{"type":"PLAYER_KILL","timestamp":1660853124339,"killerPlayfabId":"47167D5CB3751A2C","killerTeam":"Blue","victimPlayfabId":"1A2F81E7C5DFF825","victimTeam":"Red","weaponName":"SteyrAUG"},{"type":"PLAYER_KILL","timestamp":1660853130857,"killerPlayfabId":"5F4BAE52BEDDF22","killerTeam":"Red","victimPlayfabId":"47167D5CB3751A2C","victimTeam":"Blue","weaponName":"Kalashnikov"},{"type":"PLAYER_KILL","timestamp":1660853135193,"killerPlayfabId":"1A2F81E7C5DFF825","killerTeam":"Red","victimPlayfabId":"84C09631ABBCDA0E","victimTeam":"Blue","weaponName":"Kalashnikov"},{"type":"PLAYER_KILL","timestamp":1660853136926,"killerPlayfabId":"47167D5CB3751A2C","killerTeam":"Blue","victimPlayfabId":"5F4BAE52BEDDF22","victimTeam":"Red","weaponName":"SteyrAUG"},{"type":"PLAYER_KILL","timestamp":1660853142032,"killerPlayfabId":"47167D5CB3751A2C","killerTeam":"Blue","victimPlayfabId":"1A2F81E7C5DFF825","victimTeam":"Red","weaponName":"SteyrAUG"},{"type":"PLAYER_KILL","timestamp":1660853142749,"killerPlayfabId":"C42975C9A8E4E66B","killerTeam":"Blue","victimPlayfabId":"C19637F2290726EB","victimTeam":"Red","weaponName":"Kalashnikov"},{"type":"PLAYER_KILL","timestamp":1660853146872,"killerPlayfabId":"5F4BAE52BEDDF22","killerTeam":"Red","victimPlayfabId":"84C09631ABBCDA0E","victimTeam":"Blue","weaponName":"Kalashnikov"},{"type":"PLAYER_KILL","timestamp":1660853146876,"killerPlayfabId":"5F4BAE52BEDDF22","killerTeam":"Red","victimPlayfabId":"47167D5CB3751A2C","victimTeam":"Blue","weaponName":"Kalashnikov"},{"type":"PLAYER_KILL","timestamp":1660853149749,"killerPlayfabId":"C42975C9A8E4E66B","killerTeam":"Blue","victimPlayfabId":"5F4BAE52BEDDF22","victimTeam":"Red","weaponName":"Kalashnikov"},{"type":"PLAYER_KILL","timestamp":1660853152481,"killerPlayfabId":"47167D5CB3751A2C","killerTeam":"Blue","victimPlayfabId":"C19637F2290726EB","victimTeam":"Red","weaponName":"RGD5"},{"type":"PLAYER_KILL","timestamp":1660853152482,"killerPlayfabId":"C19637F2290726EB","killerTeam":"Red","victimPlayfabId":"47167D5CB3751A2C","victimTeam":"Blue","weaponName":"Knife"},{"type":"PLAYER_KILL","timestamp":1660853153935,"killerPlayfabId":"C42975C9A8E4E66B","killerTeam":"Blue","victimPlayfabId":"1A2F81E7C5DFF825","victimTeam":"Red","weaponName":"Knife"},{"type":"PLAYER_KILL","timestamp":1660853160028,"killerPlayfabId":"5F4BAE52BEDDF22","killerTeam":"Red","victimPlayfabId":"C42975C9A8E4E66B","victimTeam":"Blue","weaponName":"Kalashnikov"},{"type":"PLAYER_KILL","timestamp":1660853161895,"killerPlayfabId":"1A2F81E7C5DFF825","killerTeam":"Red","victimPlayfabId":"47167D5CB3751A2C","victimTeam":"Blue","weaponName":"Knife"},{"type":"PLAYER_KILL","timestamp":1660853168214,"killerPlayfabId":"47167D5CB3751A2C","killerTeam":"Blue","victimPlayfabId":"1A2F81E7C5DFF825","victimTeam":"Red","weaponName":"SteyrAUG"},{"type":"PLAYER_KILL","timestamp":1660853168497,"killerPlayfabId":"C19637F2290726EB","killerTeam":"Red","victimPlayfabId":"84C09631ABBCDA0E","victimTeam":"Blue","weaponName":"SteyrAUG"},{"type":"FLAG_CAP","timestamp":1660853170118,"cappingTeam":"Red","playfabId":"C19637F2290726EB"},{"type":"PLAYER_KILL","timestamp":1660853170915,"killerPlayfabId":"47167D5CB3751A2C","killerTeam":"Blue","victimPlayfabId":"5F4BAE52BEDDF22","victimTeam":"Red","weaponName":"SteyrAUG"},{"type":"PLAYER_KILL","timestamp":1660853173065,"killerPlayfabId":"C42975C9A8E4E66B","killerTeam":"Blue","victimPlayfabId":"C19637F2290726EB","victimTeam":"Red","weaponName":"Knife"},{"type":"PLAYER_KILL","timestamp":1660853178010,"killerPlayfabId":"C19637F2290726EB","killerTeam":"Red","victimPlayfabId":"47167D5CB3751A2C","victimTeam":"Blue","weaponName":"RGD5"},{"type":"PLAYER_KILL","timestamp":1660853178093,"killerPlayfabId":"47167D5CB3751A2C","killerTeam":"Blue","victimPlayfabId":"1A2F81E7C5DFF825","victimTeam":"Red","weaponName":"Knife"},{"type":"FLAG_CAP","timestamp":1660853180297,"cappingTeam":"Blue","playfabId":"C42975C9A8E4E66B"},{"type":"PLAYER_KILL","timestamp":1660853182962,"killerPlayfabId":"C42975C9A8E4E66B","killerTeam":"Blue","victimPlayfabId":"5F4BAE52BEDDF22","victimTeam":"Red","weaponName":"Kalashnikov"},{"type":"PLAYER_KILL","timestamp":1660853188247,"killerPlayfabId":"5F4BAE52BEDDF22","killerTeam":"Red","victimPlayfabId":"84C09631ABBCDA0E","victimTeam":"Blue","weaponName":"RGD5"},{"type":"PLAYER_KILL","timestamp":1660853188530,"killerPlayfabId":"47167D5CB3751A2C","killerTeam":"Blue","victimPlayfabId":"1A2F81E7C5DFF825","victimTeam":"Red","weaponName":"SteyrAUG"},{"type":"PLAYER_KILL","timestamp":1660853194499,"killerPlayfabId":"1A2F81E7C5DFF825","killerTeam":"Red","victimPlayfabId":"C42975C9A8E4E66B","victimTeam":"Blue","weaponName":"Kalashnikov"},{"type":"PLAYER_KILL","timestamp":1660853195500,"killerPlayfabId":"5F4BAE52BEDDF22","killerTeam":"Red","victimPlayfabId":"47167D5CB3751A2C","victimTeam":"Blue","weaponName":"Kalashnikov"},{"type":"PLAYER_KILL","timestamp":1660853198467,"killerPlayfabId":"5F4BAE52BEDDF22","killerTeam":"Red","victimPlayfabId":"84C09631ABBCDA0E","victimTeam":"Blue","weaponName":"RPG"},{"type":"PLAYER_KILL","timestamp":1660853198500,"killerPlayfabId":"84C09631ABBCDA0E","killerTeam":"Blue","victimPlayfabId":"5F4BAE52BEDDF22","victimTeam":"Red","weaponName":"Kalashnikov"},{"type":"PLAYER_KILL","timestamp":1660853203503,"killerPlayfabId":"C42975C9A8E4E66B","killerTeam":"Blue","victimPlayfabId":"1A2F81E7C5DFF825","victimTeam":"Red","weaponName":"Kalashnikov"},{"type":"PLAYER_KILL","timestamp":1660853206329,"killerPlayfabId":"47167D5CB3751A2C","killerTeam":"Blue","victimPlayfabId":"C19637F2290726EB","victimTeam":"Red","weaponName":"SteyrAUG"},{"type":"PLAYER_KILL","timestamp":1660853207493,"killerPlayfabId":"5F4BAE52BEDDF22","killerTeam":"Red","victimPlayfabId":"C42975C9A8E4E66B","victimTeam":"Blue","weaponName":"RGD5"},{"type":"PLAYER_KILL","timestamp":1660853207494,"killerPlayfabId":"C42975C9A8E4E66B","killerTeam":"Blue","victimPlayfabId":"5F4BAE52BEDDF22","victimTeam":"Red","weaponName":"Kalashnikov"},{"type":"PLAYER_KILL","timestamp":1660853212623,"killerPlayfabId":"C19637F2290726EB","killerTeam":"Red","victimPlayfabId":"84C09631ABBCDA0E","victimTeam":"Blue","weaponName":"SteyrAUG"},{"type":"PLAYER_KILL","timestamp":1660853215662,"killerPlayfabId":"C42975C9A8E4E66B","killerTeam":"Blue","victimPlayfabId":"1A2F81E7C5DFF825","victimTeam":"Red","weaponName":"Kalashnikov"},{"type":"PLAYER_KILL","timestamp":1660853216078,"killerPlayfabId":"C19637F2290726EB","killerTeam":"Red","victimPlayfabId":"47167D5CB3751A2C","victimTeam":"Blue","weaponName":"SteyrAUG"},{"type":"PLAYER_KILL","timestamp":1660853224036,"killerPlayfabId":"47167D5CB3751A2C","killerTeam":"Blue","victimPlayfabId":"C19637F2290726EB","victimTeam":"Red","weaponName":"SteyrAUG"},{"type":"PLAYER_KILL","timestamp":1660853225120,"killerPlayfabId":"C42975C9A8E4E66B","killerTeam":"Blue","victimPlayfabId":"5F4BAE52BEDDF22","victimTeam":"Red","weaponName":"Kalashnikov"},{"type":"PLAYER_KILL","timestamp":1660853227421,"killerPlayfabId":"1A2F81E7C5DFF825","killerTeam":"Red","victimPlayfabId":"84C09631ABBCDA0E","victimTeam":"Blue","weaponName":"Kalashnikov"},{"type":"PLAYER_KILL","timestamp":1660853230105,"killerPlayfabId":"5F4BAE52BEDDF22","killerTeam":"Red","victimPlayfabId":"47167D5CB3751A2C","victimTeam":"Blue","weaponName":"RGD5"},{"type":"PLAYER_KILL","timestamp":1660853231239,"killerPlayfabId":"C42975C9A8E4E66B","killerTeam":"Blue","victimPlayfabId":"1A2F81E7C5DFF825","victimTeam":"Red","weaponName":"Kalashnikov"},{"type":"PLAYER_KILL","timestamp":1660853236407,"killerPlayfabId":"5F4BAE52BEDDF22","killerTeam":"Red","victimPlayfabId":"C42975C9A8E4E66B","victimTeam":"Blue","weaponName":"RPG"},{"type":"PLAYER_KILL","timestamp":1660853238725,"killerPlayfabId":"47167D5CB3751A2C","killerTeam":"Blue","victimPlayfabId":"5F4BAE52BEDDF22","victimTeam":"Red","weaponName":"SteyrAUG"}],"result":{"isTie":false,"winner":"Blue"},"blueCaps":2,"redCaps":1,"playerKillsAndDeaths":{"84C09631ABBCDA0E":{"kills":7,"deaths":18},"C42975C9A8E4E66B":{"kills":24,"deaths":16},"47167D5CB3751A2C":{"kills":25,"deaths":16},"1A2F81E7C5DFF825":{"kills":7,"deaths":21},"C19637F2290726EB":{"kills":22,"deaths":18},"5F4BAE52BEDDF22":{"kills":21,"deaths":17}}}],"teamNames":{"Blue":"Blue","Red":"Red"},"gameForfeitedWithRemainingTeam":null,"playerKillsAndDeaths":{"84C09631ABBCDA0E":{"kills":21,"deaths":29},"C42975C9A8E4E66B":{"kills":49,"deaths":35},"47167D5CB3751A2C":{"kills":45,"deaths":31},"1A2F81E7C5DFF825":{"kills":17,"deaths":43},"C19637F2290726EB":{"kills":42,"deaths":37},"5F4BAE52BEDDF22":{"kills":36,"deaths":35}},"gameNumberInPlaylist":1214}